.gitignore
.travis.yml
IDEAS
LICENSE.txt
MANIFEST.in
README.rst
setup.cfg
setup.py
bin/labnote
docs/Makefile
docs/conf.py
docs/configuration.rst
docs/development.rst
docs/features.rst
docs/index.rst
docs/installation.rst
docs/make.bat
docs/_build/doctrees/configuration.doctree
docs/_build/doctrees/development.doctree
docs/_build/doctrees/environment.pickle
docs/_build/doctrees/features.doctree
docs/_build/doctrees/index.doctree
docs/_build/doctrees/installation.doctree
docs/_build/html/.buildinfo
docs/_build/html/configuration.html
docs/_build/html/development.html
docs/_build/html/features.html
docs/_build/html/genindex.html
docs/_build/html/index.html
docs/_build/html/installation.html
docs/_build/html/objects.inv
docs/_build/html/search.html
docs/_build/html/searchindex.js
docs/_build/html/_images/category_example.png
docs/_build/html/_images/example_screenshot.png
docs/_build/html/_sources/configuration.txt
docs/_build/html/_sources/development.txt
docs/_build/html/_sources/features.txt
docs/_build/html/_sources/index.txt
docs/_build/html/_sources/installation.txt
docs/_build/html/_static/ajax-loader.gif
docs/_build/html/_static/alabaster.css
docs/_build/html/_static/basic.css
docs/_build/html/_static/comment-bright.png
docs/_build/html/_static/comment-close.png
docs/_build/html/_static/comment.png
docs/_build/html/_static/doctools.js
docs/_build/html/_static/down-pressed.png
docs/_build/html/_static/down.png
docs/_build/html/_static/file.png
docs/_build/html/_static/jquery-1.11.1.js
docs/_build/html/_static/jquery.js
docs/_build/html/_static/minus.png
docs/_build/html/_static/plus.png
docs/_build/html/_static/pygments.css
docs/_build/html/_static/searchtools.js
docs/_build/html/_static/underscore-1.3.1.js
docs/_build/html/_static/underscore.js
docs/_build/html/_static/up-pressed.png
docs/_build/html/_static/up.png
docs/_build/html/_static/websupport.js
docs/images/category_example.png
docs/images/example_screenshot.png
docs/images/example_screenshot_bioinf.png
labnote.egg-info/PKG-INFO
labnote.egg-info/SOURCES.txt
labnote.egg-info/dependency_links.txt
labnote.egg-info/not-zip-safe
labnote.egg-info/requires.txt
labnote.egg-info/top_level.txt
