Metadata-Version: 1.1
Name: labnote
Version: 0.9.3
Summary: Flexible and lightweight tool for generating HTML-based electronic lab notebooks
Home-page: https://github.com/khughitt/labnote
Author: Keith Hughitt
Author-email: khughitt@umd.edu
License: BSD
Download-URL: https://github.com/khughitt/labnote/tarball/0.9.3
Platform: Linux
Platform: Solaris
Platform: Mac OS-X
Platform: Unix
Platform: Windows
Classifier: Development Status :: 4 - Beta
Classifier: Intended Audience :: Science/Research
Classifier: License :: OSI Approved :: BSD License
Classifier: Programming Language :: Python
Classifier: Programming Language :: Python :: 3
Classifier: Topic :: Scientific/Engineering
Classifier: Topic :: Scientific/Engineering :: Bio-Informatics
Classifier: Operating System :: Microsoft :: Windows
Classifier: Operating System :: POSIX
Classifier: Operating System :: Unix
Classifier: Operating System :: MacOS
Provides: labnote
